evbus/conf.py
evbus/version.py
evbus/evbus/acct.py
evbus/evbus/broker.py
evbus/evbus/init.py
evbus/ingress/internal.py
evbus/ingress/contracts/init.py
evbus/log/queue.py
evbus/match/glob.py
evbus/match/init.py
evbus/match/regex.py
evbus/match/contracts/init.py
pop_evbus-7.0.1.dist-info/LICENSE
pop_evbus-7.0.1.dist-info/METADATA
pop_evbus-7.0.1.dist-info/WHEEL
pop_evbus-7.0.1.dist-info/top_level.txt
pop_evbus-7.0.1.dist-info/RECORD
