Metadata-Version: 2.1
Name: pop-evbus
Version: 7.0.1
Summary: Event propagation to configured ingress plugins
Home-page: https://gitlab.com/saltstack/pop/evbus
Author: Tyler Johnson
Author-email: tyjohnson@vmware.com
Classifier: Environment :: Console
Classifier: Intended Audience :: Developers
Classifier: Intended Audience :: Information Technology
Classifier: Intended Audience :: System Administrators
Classifier: Operating System :: OS Independent
Classifier: Programming Language :: Python
Classifier: Programming Language :: Python :: 3.8
Classifier: Programming Language :: Python :: 3.9
Classifier: Programming Language :: Python :: 3.10
Classifier: Programming Language :: Python :: 3.11
Classifier: Development Status :: 5 - Production/Stable
Requires-Python: >=3.8
License-File: LICENSE
Requires-Dist: acct >=8.0.1
Requires-Dist: msgpack
Requires-Dist: pop >=21
Requires-Dist: pop-serial
Requires-Dist: rend
Requires-Dist: pyyaml >=6.0.1
